OpenApiLibCore/__init__.py
OpenApiLibCore/dto_base.py
OpenApiLibCore/dto_utils.py
OpenApiLibCore/oas_cache.py
OpenApiLibCore/openapi_libcore.libspec
OpenApiLibCore/openapi_libcore.py
OpenApiLibCore/py.typed
OpenApiLibCore/value_utils.py
robotframework_openapi_libcore-1.11.0.dist-info/LICENSE
robotframework_openapi_libcore-1.11.0.dist-info/METADATA
robotframework_openapi_libcore-1.11.0.dist-info/WHEEL
robotframework_openapi_libcore-1.11.0.dist-info/RECORD
