Metadata-Version: 2.1
Name: robotframework-openapi-libcore
Version: 1.11.0
Summary: A Robot Framework library to facilitate library development for OpenAPI / Swagger APIs.
Home-page: https://github.com/MarketSquare/robotframework-openapi-libcore
License: Apache-2.0
Author: Robin Mackaij
Author-email: r.a.mackaij@gmail.com
Maintainer: Robin Mackaij
Maintainer-email: r.a.mackaij@gmail.com
Requires-Python: >=3.8,<4.0
Classifier: Framework :: Robot Framework
Classifier: License :: OSI Approved :: Apache Software License
Classifier: Operating System :: OS Independent
Classifier: Programming Language :: Python :: 3
Classifier: Programming Language :: Python :: 3.8
Classifier: Programming Language :: Python :: 3.9
Classifier: Programming Language :: Python :: 3.10
Classifier: Programming Language :: Python :: 3.11
Classifier: Programming Language :: Python :: 3.12
Classifier: Topic :: Software Development :: Testing
Classifier: Topic :: Software Development :: Testing :: Acceptance
Requires-Dist: Faker (>=11)
Requires-Dist: openapi-core (>=0.18.0,<0.19.0)
Requires-Dist: prance[cli] (>=23.6,<24.0)
Requires-Dist: requests (>=2.27,<3.0)
Requires-Dist: robotframework (>=4)
Requires-Dist: rstr (>=3,<4)
